cachable/__init__.py
cachable/cachable_functions.py
cachable/cached_objects.py
cachable/file_names.py
cachable/loaders.py
cachable/params.py
cachable-0.0.1.dist-info/LICENSE
cachable-0.0.1.dist-info/METADATA
cachable-0.0.1.dist-info/WHEEL
cachable-0.0.1.dist-info/top_level.txt
cachable-0.0.1.dist-info/RECORD
