Metadata-Version: 2.1
Name: cachable
Version: 0.0.1
Summary: decorators for easily caching function results
Home-page: https://github.com/klasleino/caching
Author: Klas Leino
Author-email: kleino@cs.cmu.edu
License: UNKNOWN
Platform: UNKNOWN
Classifier: Programming Language :: Python :: 3
Classifier: License :: OSI Approved :: MIT License
Classifier: Operating System :: OS Independent
Requires-Python: >=3.6
